Metadata-Version: 2.4
Name: ethernity-cloud-runner-py
Version: 0.3.4
Summary: Ethernity Cloud Runner Python
Home-page: https://github.com/ethernity-cloud/ethernity-cloud-runner-py
Author: Ethernity Cloud Team
Author-email: contact@ethernity.cloud
License-File: LICENSE
Requires-Dist: web3==7.6.0
Requires-Dist: eth-typing
Requires-Dist: ipfshttpclient
Requires-Dist: python-dotenv
Requires-Dist: tinyec
Requires-Dist: cryptography
Requires-Dist: requests
Requires-Dist: pyasn1
Requires-Dist: pynacl
Requires-Dist: ckzg==2.0.1
Dynamic: author
Dynamic: author-email
Dynamic: description
Dynamic: description-content-type
Dynamic: home-page
Dynamic: license-file
Dynamic: requires-dist
Dynamic: summary
